{
  "title": "What is Solar Panel Efficiency?",
  "description": "With the worldwide rising solar energy adoption, solar panel efficiency has become an important aspect of energy production. This blog helps us understand what solar panel efficiency is and the factors affecting and improving it.",
  "featuredImage": "https://taypro.in/wp-content/uploads/2025/05/Feature-IMage4-1.webp",
  "author": "Taypro Team",
  "slug": "what-is-solar-panel-efficiency",
  "publishDate": "2025-10-16T11:20:32.129Z",
  "createdAt": "2025-10-16T11:20:32.129Z"
}